<?xml version="1.0" encoding="UTF-8" standalone="yes" ?>




<item>
<title> Hichki  (2018) </title>
<link>http://sv7.uploadt.com/Movie/2018.05/Hichki.2018.Hindi.720p.BrRip.x264.ReXStAr_AVADL.ME.mkv</link>
<thumbnail>https://image.tmdb.org/t/p/original/vawEeGTT115cJBFezPWiit0j533.jpg</thumbnail>
</item>

<item>
<title> Sketch (2018) </title>
<link>http://sv7.uploadt.com/Movie/2018.02/Sketch.2018.720p.HDRip.x264_AVADL.ME.mkv</link>
<thumbnail>https://image.tmdb.org/t/p/original/meJjODI5tTJAvyxhmnDyW8qLPRj.jpg</thumbnail>
</item>

<item>
<title> Baaghi 2  (2018) </title>
<link>http://sv7.uploadt.com/Movie/2018.04/Baaghi.2.2018.Hindi.720p.HDRip.x264_AVADL.ME.mkv</link>
<thumbnail>https://image.tmdb.org/t/p/original/gwX6mKjfxBYbq46CoIpcxIAmIMx.jpg</thumbnail>
</item>

<item>
<title> Behen Hogi Teri  (2018) </title>
<link>http://dl.filmbaroon.net/film/2017/Behen.Hogi.Teri.2017.720p.WEB-DL.SaNiG_Filmbaroon.net.mkv</link>
<thumbnail>https://image.tmdb.org/t/p/original/eRAucCRpBn2VbhtDCm74QpV4EMA.jpg</thumbnail>
</item>

<item>
<title> The Boy With The TopKnot  (2018) </title>
<link>http://sv7.uploadet.ir/Movie/2017.11/x265.HEVC/The.Boy.With.The.Topknot.2017.720p.HDTV.x265.HEVC_AVADL.CO.mkv</link>
<thumbnail>https://image.tmdb.org/t/p/original/kCzmWSws3VICpxlkGKQF1msyS0N.jpg</thumbnail>
</item>

<item>
<title> Running Shaadi  (2018) </title>
<link>http://dl.filmbaroon.net/Running_Shaadi_2017_DVDRip_720p_NBY.mkv</link>
<thumbnail>https://image.tmdb.org/t/p/original/5MjR790oR7UMTHxCcQw4J9mbne6.jpg</thumbnail>
</item>

<item>
<title> Bhaagamathie  (2018) </title>
<link>http://dl.filmbaroon.net/film/2016/Hotel.Salvation.2016.720p.Ganool.mkv</link>
<thumbnail>https://image.tmdb.org/t/p/original/f00V2b7nZtmmSSZkIBbN1PQUWBt.jpg</thumbnail>
</item>

<item>
<title> Hotel Salvation  (2018) </title>
<link>http://dl.filmbaroon.net/film/2016/Hotel.Salvation.2016.720p.Ganool.mkv</link>
<thumbnail>https://image.tmdb.org/t/p/original/4KU7HqRPbl4ZTELz2uRDQYCLSOq.jpg</thumbnail>
</item>

<item>
<title> Channa Mereya  (2018) </title>
<link>http://dl.filmbaroon.net/film/2017/Channa.Mereya.2017.720p.WEBRip.SaNiG.mkv</link>
<thumbnail>https://image.tmdb.org/t/p/original/iz7ql5RBTR3GmddEYJEaYFF7ZMY.jpg</thumbnail>
</item>

<item>
<title> Shaadi Mein Zaroor Aana  (2018) </title>
<link>http://dl.filmbaroon.net/film/2017/Shaadi.Mein.Zaroor.Aana.2017.720p.WEB-DL.mkv</link>
<thumbnail>https://image.tmdb.org/t/p/original/hSpzMrohhzT7EQcvMIpXizP2hx4.jpg</thumbnail>
</item>

<item>
<title> Tutak Tutak Tutiya (2018) </title>
<link>http://dl.filmbaroon.net/film/2016/Tutak.Tutak.Tutiya.2016.720p.WEB-DL.SaNiG.mkv</link>
<thumbnail>https://image.tmdb.org/t/p/original/4KDIUNJLFGglyKvKlkBmxiq1ArR.jpg</thumbnail>
</item>

<item>
<title> Love Per Square Foot (2018) </title>
<link>http://dl.filmbaroon.net/film/2018/Love.Per.Square.Foot.2018.720p.WEB-DL.x265_filmbaroon.mkv</link>
<thumbnail>https://image.tmdb.org/t/p/original/hELQ0htEiE0NHWvmVrPZ4sSrkBF.jpg</thumbnail>
</item>

<item>
<title> Aiyaary (2018) </title>
<link>http://dl.filmbaroon.net/film/2018/Aiyaary.2018.720p.HDTS.SaNiG.mkv</link>
<thumbnail>https://image.tmdb.org/t/p/original/f3bgWjveSdFmCipmHi1JIpDCRgM.jpg</thumbnail>
</item>

<item>
<title> Brahmotsavam  (2018) </title>
<link>http://dl.filmbaroon.net/film/2016/Brahmotsavam.2016.720p.WEB-DL.Filmbaroon.net.mkv</link>
<thumbnail>https://image.tmdb.org/t/p/original/k1mV662mmYJknhwCwOVOpPunvFa.jpg</thumbnail>
</item>

<item>
<title> Padman  (2018) </title>
<link>http://sv7.uploadt.com/Movie/2018.04/Padman.2018.Hindi.720p.PreDvDRip.x264.AAC_AVADL.ME.mkv</link>
<thumbnail>https://image.tmdb.org/t/p/original/x7o4o2N1wzY3QVQWNNj905aJxoQ.jpg</thumbnail>
</item>

<item>
<title> Dora  (2018) </title>
<link>http://dl.filmbaroon.net/film/2017/Dora.2017.720p.HDRip.SaNiG.mkv</link>
<thumbnail>https://image.tmdb.org/t/p/original/mOiGGMRrjXQDeVxVA1LaVhi4nNr.jpg</thumbnail>
</item>

<item>
<title> Qarib Qarib Singlle  (2018) </title>
<link>http://dl.filmbaroon.net/film/2017/Qarib.Qarib.Singlle.2017.720p.WEB-DL.SaNiG_Filmbaroon.net.mkv</link>
<thumbnail>https://image.tmdb.org/t/p/original/kuv9XSflB7SJhqtp0f7TWl8XaEa.jpg</thumbnail>
</item>

<item>
<title> Kuldip Patwal: I Didn't Do It!   (2018) </title>
<link>http://103.67.198.6/uploaded-videos/Kuldip%20Patwal-%20I%20Didn%E2%80%99t%20Do%20It!%20-%20Dekhvhai.MP4</link>
<thumbnail>https://image.tmdb.org/t/p/original/zJdYnq63UHhHPcoCf4Q5XzCZDHR.jpg</thumbnail>
</item>

<item>
<title> Indu Sarkar  (2018) </title>
<link>http://dl.filmbaroon.net/Indu.Sarkar.2017.720p.HDRip.SaNiG.mkv</link>
<thumbnail>https://image.tmdb.org/t/p/original/qhqXfpQBPjzgaaIuulGpyzGCNgs.jpg</thumbnail>
</item>

<item>
<title> Padmaavat (2018) </title>
<link>http://sv7.uploadt.com/Movie/2018.03/Padmaavat.2018.720p.WEB-DL_AVADL.ME.mkv</link>
<thumbnail>https://image.tmdb.org/t/p/original/9NcJmRiEpMNLBl2ek5PF4SVDuHS.jpg</thumbnail>
</item>

<item>
<title> Nenu Local (2018) </title>
<link>http://dl.filmbaroon.net/Nenu.Local.2017.720p.WEB-DL.SaNiG.mkv</link>
<thumbnail>https://images-na.ssl-images-amazon.com/images/M/MV5BMTY1YzQzNTUtOWZlNS00YmRjLTk3ZmMtMTNhNDIyNTlhNjI5L2ltYWdlXkEyXkFqcGdeQXVyNjczNzIxOTk@._V1_SY1000_CR0,0,706,1000_AL_.jpg</thumbnail>
</item>

<item>
<title> Mukkabaaz (2017) </title>
<link>http://sv7.uploadt.com/Movie/2018.04/Mukkabaaz%202018%20720p%20WEBRip%20x264_AVADL.ME.mkv</link>
<thumbnail>https://image.tmdb.org/t/p/original/na0VckuAKuP9hznMQ6NuijGX6Pl.jpg</thumbnail>
</item>

<item>
<title> Aval (2017) </title>
<link>http://dl.filmbaroon.net/The.House.Next.Door.2017.720p.WEB-DL.SaNiG.mkv</link>
<thumbnail>https://image.tmdb.org/t/p/original/nORFzELoKBeFPVdN5ia7fLwzPbT.jpg</thumbnail>
</item>

<item>
<title> Tumhari Sulu  (2017) </title>
<link>http://sv7.uploadt.com/Movie/2018.02/Tumhari.Sulu.2017.Hindi.720p.WEBRip_AVADL.ME.mkv</link>
<thumbnail>https://image.tmdb.org/t/p/original/flDkxIgrQFDn0zKpbkVg3zzkeED.jpg</thumbnail>
</item>

<item>
<title> Kaalakaandi (2017) </title>
<link>http://dl8.uploadt.com/Movie/2018.05/Kaalakaandi.2018.Hindi.720p.WEB-HD.x264_AVADL.ME.mkv</link>
<thumbnail>https://image.tmdb.org/t/p/original/o6JvSCmwSmfTjfcRNh0FbfUzVXt.jpg</thumbnail>
</item>

<item>
<title> Arjun Reddy (2017) </title>
<link>http://dl.filmbaroon.net/Arjun_Reddy_2017_Filmbaroon.com.mkv</link>
<thumbnail>https://image.tmdb.org/t/p/original/mTxbUREJ42WbLekdrW0VoZmgG8E.jpg</thumbnail>
</item>

<item>
<title> Jaya Janaki Nayaka (2017) </title>
<link>http://dl.filmbaroon.net/Jaya_Janaki_Nayaka_2017_720p_WEB-DL.mkv</link>
<thumbnail>https://image.tmdb.org/t/p/original/eB2aF05kTEcH9Bhu5JY7BNNrgAm.jpg</thumbnail>
</item>

<item>
<title> Ezra  (2017) </title>
<link>http://dl.filmbaroon.net/Ezra.2017.HDRip.720p.SaNiG.Filmbaroon.com.mkv</link>
<thumbnail>https://image.tmdb.org/t/p/original/9HqpA6EvX9Ua8bxSpsMxCZgagBR.jpg</thumbnail>
</item>

<item>
<title> Vikram Vedha (2017) </title>
<link>http://dl.filmbaroon.net/Vikram_Vedha_2017_HDRip_720p_NM_filmbaroon.com.mkv</link>
<thumbnail>https://image.tmdb.org/t/p/original/ob9YxdzRu5lfKgz0PNrlL45dorf.jpg</thumbnail>
</item>

<item>
<title> Kaashmora   (2017) </title>
<link>http://103.67.198.6/uploaded-videos/Kaashmora%20(2017)%20New%20Released%20Full%20Hindi%20Dubbed%20Movie%20-%20Karthi,%20Nayanthara,%20Vivek%20-%20YouTube.MP4</link>
<thumbnail>https://images-na.ssl-images-amazon.com/images/M/MV5BZjBiZDc2YWMtYTdhZi00YTJiLWJkOGItZTk2NmEwN2FlY2NlXkEyXkFqcGdeQXVyMjYwMDk5NjE@._V1_.jpg</thumbnail>
</item>

<item>
<title> Bairavaa   (2017) </title>
<link>http://103.67.198.6/uploaded-videos/Bhairava%20(Bairavaa)%202017%20New%20Released%20Full%20Hindi%20Dubbed%20Movie%20-%20Vijay,%20Keerthy%20Suresh%20-%20YouTube.MKV</link>
<thumbnail>https://images-na.ssl-images-amazon.com/images/M/MV5BM2NkZjNjNDYtYjc4My00MmNjLWJiZDAtOWEwY2VkOWMxMTA1XkEyXkFqcGdeQXVyODE0NjUxNzY@._V1_.jpg</thumbnail>
</item>

<item>
<title> Hello   (2017) </title>
<link>http://dl.filmbaroon.net/Hello.2017.HDRip.720p.SaNiG.mkv</link>
<thumbnail>https://image.tmdb.org/t/p/original/7Vl7Yx3rvVv0oWHakmDmc22cGDZ.jpg</thumbnail>
</item>

<item>
<title> Main Hi Raja Main Hi Mantri   (2017) </title>
<link>http://103.67.198.6/uploaded-videos/Main%20Hi%20Raja%20Main%20Hi%20Mantri%20(2017)%20New%20Released%20Hindi%20Dubbed%20Full%20Movie%20-%20Rana%20Daggubati,%20Kajal%20-%20YouTube.MKV</link>
<thumbnail>https://image.tmdb.org/t/p/original/eGUL4lndNa8hTR7nqBmZacI9iiH.jpg</thumbnail>
</item>

<item>
<title> Monsoon Shootout   (2017) </title>
<link>http://dl.filmbaroon.net/Monsoon.Shootout.2017.Pre-DVDRip.SaNiG.mkv</link>
<thumbnail>https://image.tmdb.org/t/p/original/gzBdH7LawD5ma2IPuGJ2M9zd1Ic.jpg</thumbnail>
</item>

<item>
<title> Heartbeats   (2017) </title>
<link>http://dl.filmbaroon.net/Heartbeats.2017.720p.YIFY.mp4</link>
<thumbnail>https://image.tmdb.org/t/p/original/29Fk3nM7FBgBa4pX2GWZAMm1SYb.jpg</thumbnail>
</item>

<item>
<title> Tiger Zinda Hai  (2017) </title>
<link>http://sv7.uploadt.com/Movie/2018.02/Tiger.Zinda.Hai.2017.720p.BrRip.x265.HEVC_AVADL.ME.mkv</link>
<thumbnail>https://image.tmdb.org/t/p/original/6EHnmwCtBhfOuoKQaHUSACV5UUJ.jpg</thumbnail>
</item>

<item>
<title> Ittefaq    (2017) </title>
<link>http://sv7.uploadt.com/Movie/2018.02/Ittefaq.2017.Hindi.720p.BrRip.AVADL.ME.mkv</link>
<thumbnail>https://image.tmdb.org/t/p/original/fiXMsmek7KTnjj8B40jIcAwO02O.jpg</thumbnail>
</item>

<item>
<title> Sarkar 3    (2017) </title>
<link>http://dl.filmbaroon.net/Sarkar_3_2017_DVDRip.mkv</link>
<thumbnail>https://image.tmdb.org/t/p/original/e7X5NFoKk1Q6aprEnz60Yb3oVNz.jpg</thumbnail>
</item>

<item>
<title> Secret Superstar (2017) </title>
<link>http://dl.filmbaroon.net/Secret.Superstar.2017.720p.HDTS.SaNiG.Filmbaroon.net.mkv</link>
<thumbnail>https://image.tmdb.org/t/p/original/qJmIyh8hyGPONq7J4fIqaCMzv2p.jpg</thumbnail>
</item>

<item>
<title> Fukrey Returns    (2017) </title>
<link>http://sv7.uploadt.com/Movie/2018.04/Fukrey.Returns.2017.720p.Amazon.WEB-DL.x264_AVADL.ME.mkv</link>
<thumbnail>https://image.tmdb.org/t/p/original/3qpFYwMtSJh7SPatd9LS1Gz1kBO.jpg</thumbnail>
</item>

<item>
<title> Tera Intezaar   (2017) </title>
<link>http://103.67.198.6/uploaded-videos/Tera-Intezaar-2017-1CD-DESIpDVDRip.mkv</link>
<thumbnail>https://images-na.ssl-images-amazon.com/images/M/MV5BOWRhMWE5NzgtMGEzNS00YjM2LWE4ZTAtZWQ4MDY3MDVkMTQxXkEyXkFqcGdeQXVyNjQ2MjQ5NzM@._V1_SY1000_CR0,0,708,1000_AL_.jpg</thumbnail>
</item>

<item>
<title> Raajakumara    (2017) </title>
<link>http://103.67.198.6/uploaded-videos/Raajakumara%20-2017.mkv</link>
<thumbnail>https://images-na.ssl-images-amazon.com/images/M/MV5BNDA5NWVhMTMtMTI4My00YjgyLWFmODYtYmE3Mzk3ZDMwZTJjL2ltYWdlL2ltYWdlXkEyXkFqcGdeQXVyNjY2OTMyOTk@._V1_.jpg</thumbnail>
</item>

<item>
<title> Mersal    (2017) </title>
<link>http://103.67.198.6/uploaded-videos/Mersal%20(2017)%20-%20WebRip%20-%20X264%20-%20ESubs%20-%20800MB%20%5bTeam%20Jaffa%5d.mp4</link>
<thumbnail>https://image.tmdb.org/t/p/original/65Q1wpRPZ5E3UVUv2V5JBbJQCcj.jpg</thumbnail>
</item>

<item>
<title> DJ: Duvvada Jagannadham    (2017) </title>
<link>http://dl.filmbaroon.net/Duvvada_Jagannadham_2017_DTHRip_720p_SaNiG.mkv</link>
<thumbnail>https://image.tmdb.org/t/p/original/w4USZ6z7vwH3tJfgvHFDkDBboPc.jpg</thumbnail>
</item>

<item>
<title> Angamaly Diaries   (2017) </title>
<link>http://sv4avadl.uploadet.ir/Movie/2017/08/Angamaly.Diaries.2017.720p.BRRip_AVADL.CO.mkv</link>
<thumbnail>https://image.tmdb.org/t/p/original/wzHtG3Sx4tauiXCsk8LAkJaKgkH.jpg</thumbnail>
</item>

<item>
<title> Firangi    (2017) </title>
<link>http://dl.filmbaroon.net/Firangi.2017.DVDScr.SaNiG.mkv</link>
<thumbnail>https://image.tmdb.org/t/p/original/Atgw2Ds1wcARZBXLq1Eoi3Ui70h.jpg</thumbnail>
</item>

<item>
<title> OMG: Oh My God!    (2017) </title>
<link>http://103.67.198.6/uploaded-videos/OMG%20Oh%20My%20God%20(2012)%5b720p%5d.mpeg</link>
<thumbnail>https://image.tmdb.org/t/p/original/w4s5bTMTvhMFbCtj8oRR6nR4aG4.jpg</thumbnail>
</item>

<item>
<title> Ok Jaanu     (2017) </title>
<link>http://dl.filmbaroon.net/Ok.Jaanu.2017.Bluray.720p.NBY.mkv</link>
<thumbnail>https://image.tmdb.org/t/p/original/m3rw5feaG87XKfAiQ3oEctKloea.jpg</thumbnail>
</item>

<item>
<title> Laali Ki Shaadi Mein Laaddoo Deewana    (2017) </title>
<link>http://103.67.198.6/uploaded-videos/Laali%20Ki%20Shaadi%20Mein%20Laaddoo%20Deewana%20-%20TimePassBD.mp4</link>
<thumbnail>https://image.tmdb.org/t/p/original/i7hh87xgYhhPsNHhY2FalW02osB.jpg</thumbnail>
</item>

<item>
<title> Chef      (2017) </title>
<link>http://dl.filmbaroon.net/Chef.2017.HDRip.480p.SaNiG.mkv</link>
<thumbnail>https://image.tmdb.org/t/p/original/vZErMgE6vKMa7VCE4uIdbUfOkKn.jpg</thumbnail>
</item>

<item>
<title> Jagga Jasoos     (2017) </title>
<link>http://sv4avadl.uploadet.ir/remote/Jagga.Jasoos.2017.720p.DvDrip_AVADL.CO.mkv</link>
<thumbnail>https://image.tmdb.org/t/p/original/aAvF8e5w4xETbx8TUesCnVFJqSF.jpg</thumbnail>
</item>

<item>
<title> Machine       (2017) </title>
<link>http://dl.filmbaroon.net/Machine_2017_DVDRip.mkv</link>
<thumbnail>https://image.tmdb.org/t/p/original/nklwQJovTTjH1FgBDNUgRIpglr.jpg</thumbnail>
</item>

<item>
<title> Bhoomi       (2017) </title>
<link>http://dl.filmbaroon.net/Bhoomi_2017_WEB-DL_720p_SaNiG.mkv</link>
<thumbnail>https://image.tmdb.org/t/p/original/zVh5RNjIcM3Wggp0Be3fGdLxz75.jpg</thumbnail>
</item>

<item>
<title> Raabta    (2017) </title>
<link>http://dl.filmbaroon.net/Raabta_2017_HDRip_720p_PaHe.mkv</link>
<thumbnail>https://image.tmdb.org/t/p/original/ovdpOhdgYqhDmy3uYGhNN16CKzQ.jpg</thumbnail>
</item>

<item>
<title> Coffee with D       (2017) </title>
<link>http://sv4avadl.uploadet.ir/Movie/2017/Coffee.with.D.2017.Hindi.720p.HDRiP.x264.AVADL.BiZ.mkv</link>
<thumbnail>https://image.tmdb.org/t/p/original/tA6iaASiCKoPFsoP9x5Ab8paTje.jpg</thumbnail>
</item>

<item>
<title> A Gentleman       (2017) </title>
<link>http://dl.filmbaroon.net/A_Gentleman_2017_HDRip_720p_SaNiG_%28Filmbaroon.com%29.mkv</link>
<thumbnail>https://image.tmdb.org/t/p/original/rsZmANIzl7Ut27uBFWGz1tgPWVs.jpg</thumbnail>
</item>

<item>
<title> Shubh Mangal Saavdhan (2017) </title>
<link>http://dl.filmbaroon.net/Shubh.Mangal.Saavdhan.2017.WEB-DL.720p.SaNiG.mkv</link>
<thumbnail>https://image.tmdb.org/t/p/original/2vqW0VNvaQYSarPQtqHTRkOKQq8.jpg</thumbnail>
</item>

<item>
<title> Mubarakan        (2017) </title>
<link>http://dl.filmbaroon.net/Mubarakan_2017_720p_SaNiG.mkv</link>
<thumbnail>https://image.tmdb.org/t/p/original/bxPzSJQtS9j2KY9NE9Nw0d0JV9w.jpg</thumbnail>
</item>

<item>
<title> Maragadha Naanayam         (2017) </title>
<link>http://dl.filmbaroon.net/Maragadha_Naanayam_2017_WEBRip_720p_%28filmbaroon.com%29.mkv</link>
<thumbnail>https://image.tmdb.org/t/p/original/5GVTGeCBCDetk7c6NNVD61CyHmD.jpg</thumbnail>
</item>

<item>
<title> Lipstick Under My Burkha      (2017) </title>
<link>http://103.67.198.6/uploaded-videos/Lipstick%20Under%20My%20Burkha-%202017.mkv</link>
<thumbnail>https://image.tmdb.org/t/p/original/watd7f9icZYuXd7ODenxw0tMAhE.jpg</thumbnail>
</item>

<item>
<title> Golmaal Again      (2017) </title>
<link>http://sv7.uploadt.com/Movie/2017.12/Golmaal.Again.2017.720p.BRRip_AVADL.ME.mkv</link>
<thumbnail>https://image.tmdb.org/t/p/original/5mnOPgQCQls7NbFuf53gDew7uzq.jpg</thumbnail>
</item>

<item>
<title> Lucknow Central       (2017) </title>
<link>http://dl.filmbaroon.net/Lucknow.Central.2017.720p.SaNiG.mkv</link>
<thumbnail>https://image.tmdb.org/t/p/original/gnGl9Djk4JCzJwFF5BhiL7nXL9Z.jpg</thumbnail>
</item>

<item>
<title> Baadshaho       (2017) </title>
<link>http://sv7.uploadet.ir/AvaDL.CO/Movie/Baadshaho.2017.Hindi.720p.HDTV-Rip.x264_AVADL.CO.mkv</link>
<thumbnail>https://image.tmdb.org/t/p/original/cSeNkoe7ZC84jTa6HKdLEzUsSYW.jpg</thumbnail>
</item>

<item>
<title> Sweetiee Weds NRI      (2017) </title>
<link>http://103.67.198.6/uploaded-videos/Sweetiee%20Weds%20NRI-2017.mkv</link>
<thumbnail>https://image.tmdb.org/t/p/original/bjOqKWAhWm0aG1waZNINUwvqpUY.jpg</thumbnail>
</item>

<item>
<title> Bareilly Ki Barfi      (2017) </title>
<link>http://dl.filmbaroon.net/Bareilly_Ki_Barfi_2017_DVDRip_720p_SaNiG.mkv</link>
<thumbnail>https://image.tmdb.org/t/p/original/3gGkq074z56JfXRBIQv5M043em2.jpg</thumbnail>
</item>

<item>
<title> Alif      (2017) </title>
<link>http://103.67.198.6/uploaded-videos/Alif.2017__720p.WEBrip__E-BOX.mp4</link>
<thumbnail>https://image.tmdb.org/t/p/original/idmBU3Q2Tktz47UpBexO2KXcTqe.jpg</thumbnail>
</item>

<item>
<title> Naam Shabana      (2017) </title>
<link>http://sv4avadl.uploadet.ir/Movie/2017/06/Naam.Shabana.2017.Hindi.720p.DVDRiP.x265.AVADL.BiZ.mkv</link>
<thumbnail>https://image.tmdb.org/t/p/original/xFHeFrOYzsHgAiZeGAjwJmDMen6.jpg</thumbnail>
</item>

<item>
<title> Jab Harry Met Sejal     (2017) </title>
<link>http://dl.filmbaroon.net/Jab_Harry_met_Sejal_2017_720p_SaNiG.mkv</link>
<thumbnail>https://image.tmdb.org/t/p/original/2hIbGcy0Ec4Dek75d3zLzwFhoPM.jpg</thumbnail>
</item>

<item>
<title> Bank Chor      (2017) </title>
<link>http://sv4avadl.uploadet.ir/Movie/2017/09/Bank.Chor.2017.720p.HDRip.x264.AVADL.CO.mkv</link>
<thumbnail>https://image.tmdb.org/t/p/original/4HAym2Y2sE0pjmVRKVHlmZ1YqYl.jpg</thumbnail>
</item>

<item>
<title> Tubelight      (2017) </title>
<link>http://sv4avadl.uploadet.ir/Movie/2017/10/Tubelight.2017.Hindi.720p.HDRip.x264_AVADL.CO.mkv</link>
<thumbnail>https://images-na.ssl-images-amazon.com/images/M/MV5BMjExNjc1NDE3M15BMl5BanBnXkFtZTgwNDA2NzM0MjI@._V1_UY268_CR6,0,182,268_AL_.jpg</thumbnail>
</item>

<item>
<title> Bahubali 2 The Conclusion      (2017) </title>
<link>http://sv4avadl.uploadet.ir/Movie/2017/08/HEVC.x265/Baahubali.2.The.Conclusion.2017.720p.BrRip.x265.HEVC.AVADL.Co.mkv</link>
<thumbnail>https://image.tmdb.org/t/p/original/sXf30F2HFpsFPXlNz7jpOySSV9I.jpg</thumbnail>
</item>

<item>
<title> The Ghazi Attack      (2017) </title>
<link>http://sv4avadl.uploadet.ir/survivor/Movie/2017/The.Ghazi.Attack.2017.720p.BrRip.x265_AVADL.BiZ.mkv</link>
<thumbnail>https://images-na.ssl-images-amazon.com/images/M/MV5BNjJjODRlNTctM2IxYS00ZGQ4LTg2ZTItMTFiOTJkM2EyNmY4L2ltYWdlXkEyXkFqcGdeQXVyNjQ2MjQ5NzM@._V1_UY268_CR3,0,182,268_AL_.jpg</thumbnail>
</item>

<item>
<title> Sultan      (2017) </title>
<link>http://dl.filmbaroon.net/film/2016/Sultan.2016.720p.Farsi.Dubbed.mkv</link>
<thumbnail>https://image.tmdb.org/t/p/original/t2CxAMMXCrfqK55ewgH2LA9b6tb.jpg</thumbnail>
</item>

<item>
<title> Jolly LLB 2       (2017) </title>
<link>http://sv4avadl.uploadet.ir/Movie/2017/Jolly.LLB.2.2017.BrRip.720p.x264.AVADL.BiZ.mkv</link>
<thumbnail>https://images-na.ssl-images-amazon.com/images/M/MV5BMDY5MzFlYzEtNTg0YS00OGM5LWI1ZDMtZDkxN2Y2OTI1NGUxL2ltYWdlL2ltYWdlXkEyXkFqcGdeQXVyMjM1NjkwMDI@._V1_UY268_CR9,0,182,268_AL_.jpg</thumbnail>
</item>

<item>
<title> Raees      (2017) </title>
<link>http://sv4avadl.uploadet.ir/Movie/2017/05/Raees.2017.BrRip.720p.x265.AVADL.BiZ.mkv</link>
<thumbnail>https://images-na.ssl-images-amazon.com/images/M/MV5BMTc2NTYwMTE1NV5BMl5BanBnXkFtZTgwODQ5MzAwMTI@._V1_UY268_CR11,0,182,268_AL_.jpg</thumbnail>
</item>

<item>
<title> Kaabil      (2017) </title>
<link>http://dl.filmbaroon.net/Kaabil.2017.720p.HDRip.mkv</link>
<thumbnail>https://images-na.ssl-images-amazon.com/images/M/MV5BNGU0MDM1ODgtZmMwNi00NWRiLTgxYWEtMjJlNjMxNjc1NzQzL2ltYWdlL2ltYWdlXkEyXkFqcGdeQXVyNDkxMzY0Mjk@._V1_UY268_CR8,0,182,268_AL_.jpg</thumbnail>
</item>

<item>
<title> Dangal       (2017) </title>
<link>http://sv4avadl.uploadet.ir/Movie/2017/06/Dangal.2016.BrRip.720p.x265.HEVC.AVADL.BiZ.mkv</link>
<thumbnail>https://images-na.ssl-images-amazon.com/images/M/MV5BMTQ4MzQzMzM2Nl5BMl5BanBnXkFtZTgwMTQ1NzU3MDI@._V1_UY268_CR4,0,182,268_AL_.jpg</thumbnail>
</item>

<item>
<title> Dear Zindagi      (2016) </title>
<link>http://dl.filmbaroon.net/Dear.Zindagi.2016.720p.BluRay.MkvCage.Filmbaroon.com.mkv</link>
<thumbnail>https://images-na.ssl-images-amazon.com/images/M/MV5BZWQzYWI3ZGMtYzgyYy00OWZkLWEwODYtNGNiMTZhODBkNzUyL2ltYWdlL2ltYWdlXkEyXkFqcGdeQXVyNjY1MTg4Mzc@._V1_UY268_CR9,0,182,268_AL_.jpg</thumbnail>
</item>

<item>
<title> Force 2      (2016) </title>
<link>http://sv4avadl.uploadet.ir/Movie/2017/Force.2.2016.720p.BRRIP.x265.HEVC.AVADL.BiZ.mkv</link>
<thumbnail>https://images-na.ssl-images-amazon.com/images/M/MV5BYmI0ZmM3ZTItODhlOC00NjcwLWJlNzItNzFmMjIxZDY1MGY0XkEyXkFqcGdeQXVyNjQ2MjQ5NzM@._V1_UY268_CR1,0,182,268_AL_.jpg</thumbnail>
</item>

<item>
<title> Ae Dil Hai Mushkil     (2016) </title>
<link>http://dl.filmbaroon.net/Ae.Dil.Hai.Mushkil.2016.Bluray.720p.ShAaNiG.mkv</link>
<thumbnail>https://images-na.ssl-images-amazon.com/images/M/MV5BMjA5MzcyNjg0Ml5BMl5BanBnXkFtZTgwOTY2NTc4OTE@._V1_UX182_CR0,0,182,268_AL_.jpg</thumbnail>
</item>

<item>
<title> Laal Rang     (2016) </title>
<link>http://dl.filmbaroon.net/Laal.Rang.2016.720p.WEB-DL.mkv</link>
<thumbnail>https://images-na.ssl-images-amazon.com/images/M/MV5BNDdmMDc5NzQtOTY0MC00NDA5LWFmMDQtNWYwYzNlODllZGY5XkEyXkFqcGdeQXVyNjY0OTkwNTI@._V1_UX182_CR0,0,182,268_AL_.jpg</thumbnail>
</item>

<item>
<title> Sairat    (2016) </title>
<link>http://dl.filmbaroon.net/Sairat.2016.720p.WEB-DL.MkvCage.mkv</link>
<thumbnail>https://image.tmdb.org/t/p/original/aABOD2h6U5aEtVZrPyNbILBBFHc.jpg</thumbnail>
</item>

<item>
<title> Banjo    (2016) </title>
<link>http://dl.filmbaroon.net/Banjo_2016_HDTV_720p_NBY_%28Filmbaroon.com%29.mkv</link>
<thumbnail>https://images-na.ssl-images-amazon.com/images/M/MV5BNzk4NTI1ZDYtYmU3MC00ZTk2LWI3OGQtZGE5OWY1ZmM2ZjE0XkEyXkFqcGdeQXVyNjQ2MjQ5NzM@._V1_UY268_CR1,0,182,268_AL_.jpg</thumbnail>
</item>

<item>
<title> Freaky Ali       (2016) </title>
<link>http://dl.filmbaroon.net/Freaky_Ali_2016_HDRip_720p_SaNiG.mkv</link>
<thumbnail>https://image.tmdb.org/t/p/original/1F0Dr6arhcfiWxifCUZqGnoBRKj.jpg</thumbnail>
</item>

<item>
<title> Kshanam    (2016) </title>
<link>http://dl.filmbaroon.net/Kshanam.2016.720p.HDRip.mkv</link>
<thumbnail>https://image.tmdb.org/t/p/original/4wJ1KYjldhKnuQxtPCNuxt1H9mG.jpg</thumbnail>
</item>

<item>
<title> 1920 London    (2016) </title>
<link>http://103.67.198.6/uploaded-videos/1920.London.2016__720p.BRrip.mkv</link>
<thumbnail>http://ia.media-imdb.com/images/M/MV5BMjQzNTQ0OTgtZjI3OC00YjBlLThlMjYtNGUzMjYwMTgwNmU1XkEyXkFqcGdeQXVyNjQ2MjQ5NzM@._V1_UY268_CR2,0,182,268_AL_.jpg</thumbnail>
</item>

<item>
<title> Phobia     (2016) </title>
<link>http://dl.filmbaroon.net/Phobia_2016_720p_WEB-DL_NM_%28filmbaroon.com%29.mkv</link>
<thumbnail>https://images-na.ssl-images-amazon.com/images/M/MV5BMDJlZjcyZjEtZmY3YS00NDRlLWI2NDYtNjk5MzE5Nzk5YWVmXkEyXkFqcGdeQXVyNjQ2MjQ5NzM@._V1_UY268_CR1,0,182,268_AL_.jpg</thumbnail>
</item>

<item>
<title> A Flying Jatt  (2016) </title>
<link>http://dl.filmbaroon.net/A_Flying_Jatt_2016_HDRip.mkv</link>
<thumbnail>http://ia.media-imdb.com/images/M/MV5BODM5Y2E2Y2QtYWU4Zi00M2ViLWE4NTctZjA0MjFmNjZmZDEwXkEyXkFqcGdeQXVyMTExNDQ2MTI@._V1_UY268_CR2,0,182,268_AL_.jpg</thumbnail>
</item>

<item>
<title> Fan (2016) </title>
<link>http://avadl.uploadt.com/DL7/Film/Fan%20%282016%29%20720p%20BrRip%20x265_AVADL.BiZ.mkv</link>
<thumbnail>http://ia.media-imdb.com/images/M/MV5BOTMzMjkwNTI0Nl5BMl5BanBnXkFtZTgwODIxMzQ1ODE@._V1_UX182_CR0,0,182,268_AL_.jpg</thumbnail>
</item>

<item>
<title> Bajirao Mastani(2016) </title>
<link>http://dl.filmbaroon.net/Bajirao_Mastani_2015_720p_Farsi_Dubbed_%28filmbaroon%29.mkv</link>
<thumbnail>http://ia.media-imdb.com/images/M/MV5BMWI3YTA1MDktYWNjOS00MTE5LTkzMTQtOWNiODY2MjIzYTQwXkEyXkFqcGdeQXVyMTExNDQ2MTI@._V1_UY268_CR1,0,182,268_AL_.jpg</thumbnail>
</item>

<item>
<title> Rocky Handsome(2016) </title>
<link>http://dl.filmbaroon.net/Rocky.Handsome.2016.720p.WEB-DL.mkv</link>
<thumbnail>http://ia.media-imdb.com/images/M/MV5BOGRkNDA0MzItYzk0ZS00YzY4LTk1YjYtMjAyZTM0YWM2YTBkXkEyXkFqcGdeQXVyMjUxMTY3ODM@._V1_UY268_CR1,0,182,268_AL_.jpg</thumbnail>
</item>

<item>
<title> Airlift (2016) </title>
<link>http://avadl.uploadt.com/DL7/Film/Airlift%20%282016%29%20720p%20BrRip%20x265_AVADL.BiZ.mkv</link>
<thumbnail>http://ia.media-imdb.com/images/M/MV5BZGE1ZTZhNmQtYzhmNC00MjE4LTg4NDUtY2I4N2Y3OTgwZjljXkEyXkFqcGdeQXVyMTExNDQ2MTI@._V1_UY268_CR1,0,182,268_AL_.jpg</thumbnail>
</item>

<item>
<title> Rangoon  (2016) </title>
<link>http://dl.filmbaroon.net/Rangoon_2017_720p.mkv</link>
<thumbnail>https://image.tmdb.org/t/p/original/tW6C3Gkx4IA1QDDW6bPhH0AEmvI.jpg</thumbnail>
</item>

<item>
<title> Ghayal Once Again  (2016) </title>
<link>http://avadl.uploadt.com/DL7/Film/Ghayal%20Once%20Again%20%282016%29%20720p%20BrRip_AVADL.BiZ.mkv</link>
<thumbnail>http://ia.media-imdb.com/images/M/MV5BMjkwZTlhYzQtMTJkZS00YWZhLThjZjktZDk1MzI4YWIwOTJhXkEyXkFqcGdeQXVyNTE0MDc0NTM@._V1_UY268_CR2,0,182,268_AL_.jpg</thumbnail>
</item>

<item>
<title> M.S. Dhoni: The Untold Story(2016) </title>
<link>http://sv4avadl.uploadet.ir/user/Movie/2016/M.S.Dhoni.2016.720p.BRRip.HEVC.AVADL.BiZ.mkv</link>
<thumbnail>https://image.tmdb.org/t/p/original/311gCwnNJgyoNEPWR9GJ2JBGJAm.jpg</thumbnail>
</item>

<item>
<title> Udta Punjab(2016) </title>
<link>http://avadl.uploadt.com/Movie/2016/08/Udta%20Punjab%20%282016%29%20720p%20DVDrip_AVADL.BiZ.mkv</link>
<thumbnail>https://image.tmdb.org/t/p/original/wFhHC3FR5RBolFLBu0iPCPyO5uK.jpg</thumbnail>
</item>

<item>
<title> Neerja(2016) </title>
<link>http://dl.filmbaroon.net/Neerja.2016.720p.Ganool.mkv</link>
<thumbnail>https://image.tmdb.org/t/p/original/kamR6xgcyhGj05NcwbH5zoGdckE.jpg</thumbnail>
</item>

<item>
<title> 7 Hours to Go (2016) </title>
<link>http://dl.filmbaroon.net/7_Hours_To_Go_2016_720p_DVDRip_NBY_%28Filmbaroon.com%29.mkv</link>
<thumbnail>https://image.tmdb.org/t/p/original/6iiHkgRPdccxqAkNPf8986NoOPy.jpg</thumbnail>
</item>

<item>
<title> Yeh Jawaani Hai Deewani (2016) </title>
<link>http://dl.filmbaroon.net/Yeh.Jawaani.Hai.Deewani.2013.720p.Ganool.mkv</link>
<thumbnail>https://images-na.ssl-images-amazon.com/images/M/MV5BODA4MjM2ODk4OF5BMl5BanBnXkFtZTcwNDgzODk1OQ@@._V1_SY1000_CR0,0,690,1000_AL_.jpg</thumbnail>
</item>