<?xml version="1.0" encoding="UTF-8" standalone="yes" ?>



<item>
<title> Episod 1 </title>
<link>https://ok.ru/videoembed/805919263341</link>
<thumbnail>https://pbs.twimg.com/media/DknMJqZXgAIKQjR.jpg</thumbnail>
<item>

<item>
<title> Episod 2 </title>
<link>https://ok.ru/videoembed/805921360493</link>
<thumbnail>https://pbs.twimg.com/media/DknMJqZXgAIKQjR.jpg</thumbnail>
<item>

<item>
<title> Episod 3 </title>
<link>https://ok.ru/videoembed/805924178541</link>
<thumbnail>https://pbs.twimg.com/media/DknMJqZXgAIKQjR.jpg</thumbnail>
<item>

<item>
<title> Episod 4 </title>
<link>https://ok.ru/videoembed/805926996589</link>
<thumbnail>https://pbs.twimg.com/media/DknMJqZXgAIKQjR.jpg</thumbnail>
<item>

<item>
<title> Episod 5 </title>
<link>https://ok.ru/videoembed/805928700525</link>
<thumbnail>https://pbs.twimg.com/media/DknMJqZXgAIKQjR.jpg</thumbnail>
<item>

<item>
<title> Episod 6 </title>
<link>https://ok.ru/videoembed/805930863213</link>
<thumbnail>https://pbs.twimg.com/media/DknMJqZXgAIKQjR.jpg</thumbnail>
<item>















