<?xml version="1.0" encoding="UTF-8" standalone="yes" ?>



<item>
<title> Episod 1 </title>
<link>https://ok.ru/videoembed/4471943858852</link>
<thumbnail>https://pbs.twimg.com/media/FDHbH4MVgAUYnUL.jpg</thumbnail>
</item>

<item>
<title> Episod 2 </title>
<link>https://ok.ru/videoembed/4477971794596</link>
<thumbnail>https://pbs.twimg.com/media/FDHbH4MVgAUYnUL.jpg</thumbnail>
</item>

<item>
<title> Episod 3 </title>
<link>https://ok.ru/videoembed/4483603434148</link>
<thumbnail>https://pbs.twimg.com/media/FDHbH4MVgAUYnUL.jpg</thumbnail>
</item>

<item>
<title> Episod 4 </title>
<link>https://ok.ru/videoembed/4491446258340</link>
<thumbnail>https://pbs.twimg.com/media/FDHbH4MVgAUYnUL.jpg</thumbnail>
</item>

<item>
<title> Episod 5 </title>
<link>https://ok.ru/videoembed/4492073503396</link>
<thumbnail>https://pbs.twimg.com/media/FDHbH4MVgAUYnUL.jpg</thumbnail>
</item>

<item>
<title> Episod 6 </title>
<link>https://ok.ru/videoembed/4514501495460</link>
<thumbnail>https://pbs.twimg.com/media/FDHbH4MVgAUYnUL.jpg</thumbnail>
</item>

<item>
<title> Episod 7 </title>
<link>https://ok.ru/videoembed/4514843986596</link>
<thumbnail>https://pbs.twimg.com/media/FDHbH4MVgAUYnUL.jpg</thumbnail>
</item>

<item>
<title> Episod 8 </title>
<link>https://ok.ru/videoembed/4515105999524</link>
<thumbnail>https://pbs.twimg.com/media/FDHbH4MVgAUYnUL.jpg</thumbnail>
</item>

<item>
<title> Episod 9 </title>
<link>https://ok.ru/videoembed/4515275803300</link>
<thumbnail>https://pbs.twimg.com/media/FDHbH4MVgAUYnUL.jpg</thumbnail>
</item>

<item>
<title> Episod 10 </title>
<link>https://ok.ru/videoembed/4515277048484</link>
<thumbnail>https://pbs.twimg.com/media/FDHbH4MVgAUYnUL.jpg</thumbnail>
</item>

